LICENSE
MANIFEST.in
README.md
requirements.txt
setup.py
MyColonyFileParser.egg-info/PKG-INFO
MyColonyFileParser.egg-info/SOURCES.txt
MyColonyFileParser.egg-info/dependency_links.txt
MyColonyFileParser.egg-info/requires.txt
MyColonyFileParser.egg-info/top_level.txt
mcfp/__init__.py
mcfp/base.py
mcfp/category.py
mcfp/categorybase.py
mcfp/config.ini
mcfp/config.py
mcfp/exceptions.py
mcfp/file.py
mcfp/filebase.py
mcfp/unit.py
mcfp/unitbase.py
mcfp/libs/cache.py
mcfp/libs/request.py
mcfp/libs/source.py