Metadata-Version: 2.1
Name: MyColonyFileParser
Version: 1.0.0
Summary: MCFP - My Colony File Parser
Home-page: https://github.com/Euxcbsks/MyColonyFileParser
Author: Euxcbsks
Author-email: hawhaw02030746@gmail.com
License: MIT
Platform: UNKNOWN
Classifier: Programming Language :: Python :: 3
Classifier: License :: OSI Approved :: MIT License
Classifier: Operating System :: OS Independent
Requires-Python: >=3.6
